Workbook

Sheet Dashboard
B2: AfriMarket - Dashboard interactif
B4: Performance commerciale, marketing et clients - juillet à décembre 2025 | O4: Zone de calcul - source des graphiques (ne pas supprimer)
B6: Ville : | D6: (Tous) | F6: Ces filtres pilotent aussi la page "Marketing & Clients". | O6: Catégorie | P6: CA | Q6: Marge brute | R6: Taux de retour | S6: Ville | T6: CA | U6: Profit | V6: Taux d'annulation
B7: Catégorie : | D7: (Tous) | O7: Électronique | P7: =SUMIFS(Données!$P$2:$P$8815,Données!$D$2:$D$8815,IF(Dashboard!$D$6="(Tous)","*",Dashboard!$D$6),Données!$E$2:$E$8815,IF(Dashboard!$D$7="(Tous)","*",Dashboard!$D$7),Données!$L$2:$L$8815,IF(Dashboard!$D$8="(Tous)","*",Dashboard!$D$8),Données!$E$2:$E$8815,"Electronique") -> 1773708 | Q7: =SUMIFS(Données!$Q$2:$Q$8815,Données!$D$2:$D$8815,IF(Dashboard!$D$6="(Tous)","*",Dashboard!$D$6),Données!$E$2:$E$8815,IF(Dashboard!$D$7="(Tous)","*",Dashboard!$D$7),Données!$L$2:$L$8815,IF(Dashboard!$D$8="(Tous)","*",Dashboard!$D$8),Données!$E$2:$E$8815,"Electronique") -> 592192.29 | R7: =IFERROR(COUNTIFS(Données!$D$2:$D$8815,IF(Dashboard!$D$6="(Tous)","*",Dashboard!$D$6),Données!$E$2:$E$8815,IF(Dashboard!$D$7="(Tous)","*",Dashboard!$D$7),Données!$L$2:$L$8815,IF(Dashboard!$D$8="(Tous)","*",Dashboard!$D$8),Données!$E$2:$E$8815,"Electronique",Données!$N$2:$N$8815,"Retournée")/COUNTIFS(Données!$D$2:$D$8815,IF(Dashboard!$D$6="(Tous)","*",Dashboard!$D$6),Données!$E$2:$E$8815,IF(Dashboard!$D$7="(Tous)","*",Dashboard!$D$7),Données!$L$2:$L$8815,IF(Dashboard!$D$8="(Tous)","*",Dashboard!$D$8),Données!$E$2:$E$8815,"Electronique"),0) -> 0.13817664 | S7: Kinshasa | T7: =SUMIFS(Données!$P$2:$P$8815,Données!$D$2:$D$8815,IF(Dashboard!$D$6="(Tous)","*",Dashboard!$D$6),Données!$E$2:$E$8815,IF(Dashboard!$D$7="(Tous)","*",Dashboard!$D$7),Données!$L$2:$L$8815,IF(Dashboard!$D$8="(Tous)","*",Dashboard!$D$8),Données!$D$2:$D$8815,"Kinshasa") -> 703835.84 | U7: =SUMIFS(Données!$R$2:$R$8815,Données!$D$2:$D$8815,IF(Dashboard!$D$6="(Tous)","*",Dashboard!$D$6),Données!$E$2:$E$8815,IF(Dashboard!$D$7="(Tous)","*",Dashboard!$D$7),Données!$L$2:$L$8815,IF(Dashboard!$D$8="(Tous)","*",Dashboard!$D$8),Données!$D$2:$D$8815,"Kinshasa") -> 197650.22 | V7: =IFERROR(COUNTIFS(Données!$D$2:$D$8815,IF(Dashboard!$D$6="(Tous)","*",Dashboard!$D$6),Données!$E$2:$E$8815,IF(Dashboard!$D$7="(Tous)","*",Dashboard!$D$7),Données!$L$2:$L$8815,IF(Dashboard!$D$8="(Tous)","*",Dashboard!$D$8),Données!$D$2:$D$8815,"Kinshasa",Données!$N$2:$N$8815,"Annulée")/COUNTIFS(Données!$D$2:$D$8815,IF(Dashboard!$D$6="(Tous)","*",Dashboard!$D$6),Données!$E$2:$E$8815,IF(Dashboard!$D$7="(Tous)","*",Dashboard!$D$7),Données!$L$2:$L$8815,IF(Dashboard!$D$8="(Tous)","*",Dashboard!$D$8),Données!$D$2:$D$8815,"Kinshasa"),0) -> 0.0023474178
B8: Canal marketing : | D8: (Tous) | O8: Maison | P8: =SUMIFS(Données!$P$2:$P$8815,Données!$D$2:$D$8815,IF(Dashboard!$D$6="(Tous)","*",Dashboard!$D$6),Données!$E$2:$E$8815,IF(Dashboard!$D$7="(Tous)","*",Dashboard!$D$7),Données!$L$2:$L$8815,IF(Dashboard!$D$8="(Tous)","*",Dashboard!$D$8),Données!$E$2:$E$8815,"Maison") -> 360060.38 | Q8: =SUMIFS(Données!$Q$2:$Q$8815,Données!$D$2:$D$8815,IF(Dashboard!$D$6="(Tous)","*",Dashboard!$D$6),Données!$E$2:$E$8815,IF(Dashboard!$D$7="(Tous)","*",Dashboard!$D$7),Données!$L$2:$L$8815,IF(Dashboard!$D$8="(Tous)","*",Dashboard!$D$8),Données!$E$2:$E$8815,"Maison") -> 119679.07 | R8: =IFERROR(COUNTIFS(Données!$D$2:$D$8815,IF(Dashboard!$D$6="(Tous)","*",Dashboard!$D$6),Données!$E$2:$E$8815,IF(Dashboard!$D$7="(Tous)","*",Dashboard!$D$7),Données!$L$2:$L$8815,IF(Dashboard!$D$8="(Tous)","*",Dashboard!$D$8),Données!$E$2:$E$8815,"Maison",Données!$N$2:$N$8815,"Retournée")/COUNTIFS(Données!$D$2:$D$8815,IF(Dashboard!$D$6="(Tous)","*",Dashboard!$D$6),Données!$E$2:$E$8815,IF(Dashboard!$D$7="(Tous)","*",Dashboard!$D$7),Données!$L$2:$L$8815,IF(Dashboard!$D$8="(Tous)","*",Dashboard!$D$8),Données!$E$2:$E$8815,"Maison"),0) -> 0.050797401 | S8: Abidjan | T8: =SUMIFS(Données!$P$2:$P$8815,Données!$D$2:$D$8815,IF(Dashboard!$D$6="(Tous)","*",Dashboard!$D$6),Données!$E$2:$E$8815,IF(Dashboard!$D$7="(Tous)","*",Dashboard!$D$7),Données!$L$2:$L$8815,IF(Dashboard!$D$8="(Tous)","*",Dashboard!$D$8),Données!$D$2:$D$8815,"Abidjan") -> 466889.2 | U8: =SUMIFS(Données!$R$2:$R$8815,Données!$D$2:$D$8815,IF(Dashboard!$D$6="(Tous)","*",Dashboard!$D$6),Données!$E$2:$E$8815,IF(Dashboard!$D$7="(Tous)","*",Dashboard!$D$7),Données!$L$2:$L$8815,IF(Dashboard!$D$8="(Tous)","*",Dashboard!$D$8),Données!$D$2:$D$8815,"Abidjan") -> 131335.7 | V8: =IFERROR(COUNTIFS(Données!$D$2:$D$8815,IF(Dashboard!$D$6="(Tous)","*",Dashboard!$D$6),Données!$E$2:$E$8815,IF(Dashboard!$D$7="(Tous)","*",Dashboard!$D$7),Données!$L$2:$L$8815,IF(Dashboard!$D$8="(Tous)","*",Dashboard!$D$8),Données!$D$2:$D$8815,"Abidjan",Données!$N$2:$N$8815,"Annulée")/COUNTIFS(Données!$D$2:$D$8815,IF(Dashboard!$D$6="(Tous)","*",Dashboard!$D$6),Données!$E$2:$E$8815,IF(Dashboard!$D$7="(Tous)","*",Dashboard!$D$7),Données!$L$2:$L$8815,IF(Dashboard!$D$8="(Tous)","*",Dashboard!$D$8),Données!$D$2:$D$8815,"Abidjan"),0) -> 0
O9: Mode | P9: =SUMIFS(Données!$P$2:$P$8815,Données!$D$2:$D$8815,IF(Dashboard!$D$6="(Tous)","*",Dashboard!$D$6),Données!$E$2:$E$8815,IF(Dashboard!$D$7="(Tous)","*",Dashboard!$D$7),Données!$L$2:$L$8815,IF(Dashboard!$D$8="(Tous)","*",Dashboard!$D$8),Données!$E$2:$E$8815,"Mode") -> 177810.96 | Q9: =SUMIFS(Données!$Q$2:$Q$8815,Données!$D$2:$D$8815,IF(Dashboard!$D$6="(Tous)","*",Dashboard!$D$6),Données!$E$2:$E$8815,IF(Dashboard!$D$7="(Tous)","*",Dashboard!$D$7),Données!$L$2:$L$8815,IF(Dashboard!$D$8="(Tous)","*",Dashboard!$D$8),Données!$E$2:$E$8815,"Mode") -> 48921.879 | R9: =IFERROR(COUNTIFS(Données!$D$2:$D$8815,IF(Dashboard!$D$6="(Tous)","*",Dashboard!$D$6),Données!$E$2:$E$8815,IF(Dashboard!$D$7="(Tous)","*",Dashboard!$D$7),Données!$L$2:$L$8815,IF(Dashboard!$D$8="(Tous)","*",Dashboard!$D$8),Données!$E$2:$E$8815,"Mode",Données!$N$2:$N$8815,"Retournée")/COUNTIFS(Données!$D$2:$D$8815,IF(Dashboard!$D$6="(Tous)","*",Dashboard!$D$6),Données!$E$2:$E$8815,IF(Dashboard!$D$7="(Tous)","*",Dashboard!$D$7),Données!$L$2:$L$8815,IF(Dashboard!$D$8="(Tous)","*",Dashboard!$D$8),Données!$E$2:$E$8815,"Mode"),0) -> 0.0746997 | S9: Douala | T9: =SUMIFS(Données!$P$2:$P$8815,Données!$D$2:$D$8815,IF(Dashboard!$D$6="(Tous)","*",Dashboard!$D$6),Données!$E$2:$E$8815,IF(Dashboard!$D$7="(Tous)","*",Dashboard!$D$7),Données!$L$2:$L$8815,IF(Dashboard!$D$8="(Tous)","*",Dashboard!$D$8),Données!$D$2:$D$8815,"Douala") -> 357464.3 | U9: =SUMIFS(Données!$R$2:$R$8815,Données!$D$2:$D$8815,IF(Dashboard!$D$6="(Tous)","*",Dashboard!$D$6),Données!$E$2:$E$8815,IF(Dashboard!$D$7="(Tous)","*",Dashboard!$D$7),Données!$L$2:$L$8815,IF(Dashboard!$D$8="(Tous)","*",Dashboard!$D$8),Données!$D$2:$D$8815,"Douala") -> 101037.23 | V9: =IFERROR(COUNTIFS(Données!$D$2:$D$8815,IF(Dashboard!$D$6="(Tous)","*",Dashboard!$D$6),Données!$E$2:$E$8815,IF(Dashboard!$D$7="(Tous)","*",Dashboard!$D$7),Données!$L$2:$L$8815,IF(Dashboard!$D$8="(Tous)","*",Dashboard!$D$8),Données!$D$2:$D$8815,"Douala",Données!$N$2:$N$8815,"Annulée")/COUNTIFS(Données!$D$2:$D$8815,IF(Dashboard!$D$6="(Tous)","*",Dashboard!$D$6),Données!$E$2:$E$8815,IF(Dashboard!$D$7="(Tous)","*",Dashboard!$D$7),Données!$L$2:$L$8815,IF(Dashboard!$D$8="(Tous)","*",Dashboard!$D$8),Données!$D$2:$D$8815,"Douala"),0) -> 0.12941176
C10: =SUMIFS(Données!$P$2:$P$8815,Données!$D$2:$D$8815,IF(Dashboard!$D$6="(Tous)","*",Dashboard!$D$6),Données!$E$2:$E$8815,IF(Dashboard!$D$7="(Tous)","*",Dashboard!$D$7),Données!$L$2:$L$8815,IF(Dashboard!$D$8="(Tous)","*",Dashboard!$D$8)) -> 2384892.6 | F10: =SUMIFS(Données!$R$2:$R$8815,Données!$D$2:$D$8815,IF(Dashboard!$D$6="(Tous)","*",Dashboard!$D$6),Données!$E$2:$E$8815,IF(Dashboard!$D$7="(Tous)","*",Dashboard!$D$7),Données!$L$2:$L$8815,IF(Dashboard!$D$8="(Tous)","*",Dashboard!$D$8)) -> 667401.7 | I10: =IFERROR(C10/(COUNTIFS(Données!$D$2:$D$8815,IF(Dashboard!$D$6="(Tous)","*",Dashboard!$D$6),Données!$E$2:$E$8815,IF(Dashboard!$D$7="(Tous)","*",Dashboard!$D$7),Données!$L$2:$L$8815,IF(Dashboard!$D$8="(Tous)","*",Dashboard!$D$8),Données!$N$2:$N$8815,"Livrée")+COUNTIFS(Données!$D$2:$D$8815,IF(Dashboard!$D$6="(Tous)","*",Dashboard!$D$6),Données!$E$2:$E$8815,IF(Dashboard!$D$7="(Tous)","*",Dashboard!$D$7),Données!$L$2:$L$8815,IF(Dashboard!$D$8="(Tous)","*",Dashboard!$D$8),Données!$N$2:$N$8815,"Retournée")),0) -> 275.93342 | O10: Beauté | P10: =SUMIFS(Données!$P$2:$P$8815,Données!$D$2:$D$8815,IF(Dashboard!$D$6="(Tous)","*",Dashboard!$D$6),Données!$E$2:$E$8815,IF(Dashboard!$D$7="(Tous)","*",Dashboard!$D$7),Données!$L$2:$L$8815,IF(Dashboard!$D$8="(Tous)","*",Dashboard!$D$8),Données!$E$2:$E$8815,"Beaute") -> 73313.198 | Q10: =SUMIFS(Données!$Q$2:$Q$8815,Données!$D$2:$D$8815,IF(Dashboard!$D$6="(Tous)","*",Dashboard!$D$6),Données!$E$2:$E$8815,IF(Dashboard!$D$7="(Tous)","*",Dashboard!$D$7),Données!$L$2:$L$8815,IF(Dashboard!$D$8="(Tous)","*",Dashboard!$D$8),Données!$E$2:$E$8815,"Beaute") -> 24434.078 | R10: =IFERROR(COUNTIFS(Données!$D$2:$D$8815,IF(Dashboard!$D$6="(Tous)","*",Dashboard!$D$6),Données!$E$2:$E$8815,IF(Dashboard!$D$7="(Tous)","*",Dashboard!$D$7),Données!$L$2:$L$8815,IF(Dashboard!$D$8="(Tous)","*",Dashboard!$D$8),Données!$E$2:$E$8815,"Beaute",Données!$N$2:$N$8815,"Retournée")/COUNTIFS(Données!$D$2:$D$8815,IF(Dashboard!$D$6="(Tous)","*",Dashboard!$D$6),Données!$E$2:$E$8815,IF(Dashboard!$D$7="(Tous)","*",Dashboard!$D$7),Données!$L$2:$L$8815,IF(Dashboard!$D$8="(Tous)","*",Dashboard!$D$8),Données!$E$2:$E$8815,"Beaute"),0) -> 0.028502122 | S10: Dakar | T10: =SUMIFS(Données!$P$2:$P$8815,Données!$D$2:$D$8815,IF(Dashboard!$D$6="(Tous)","*",Dashboard!$D$6),Données!$E$2:$E$8815,IF(Dashboard!$D$7="(Tous)","*",Dashboard!$D$7),Données!$L$2:$L$8815,IF(Dashboard!$D$8="(Tous)","*",Dashboard!$D$8),Données!$D$2:$D$8815,"Dakar") -> 320084.32 | U10: =SUMIFS(Données!$R$2:$R$8815,Données!$D$2:$D$8815,IF(Dashboard!$D$6="(Tous)","*",Dashboard!$D$6),Données!$E$2:$E$8815,IF(Dashboard!$D$7="(Tous)","*",Dashboard!$D$7),Données!$L$2:$L$8815,IF(Dashboard!$D$8="(Tous)","*",Dashboard!$D$8),Données!$D$2:$D$8815,"Dakar") -> 89056.994 | V10: =IFERROR(COUNTIFS(Données!$D$2:$D$8815,IF(Dashboard!$D$6="(Tous)","*",Dashboard!$D$6),Données!$E$2:$E$8815,IF(Dashboard!$D$7="(Tous)","*",Dashboard!$D$7),Données!$L$2:$L$8815,IF(Dashboard!$D$8="(Tous)","*",Dashboard!$D$8),Données!$D$2:$D$8815,"Dakar",Données!$N$2:$N$8815,"Annulée")/COUNTIFS(Données!$D$2:$D$8815,IF(Dashboard!$D$6="(Tous)","*",Dashboard!$D$6),Données!$E$2:$E$8815,IF(Dashboard!$D$7="(Tous)","*",Dashboard!$D$7),Données!$L$2:$L$8815,IF(Dashboard!$D$8="(Tous)","*",Dashboard!$D$8),Données!$D$2:$D$8815,"Dakar"),0) -> 0
S11: Lomé | T11: =SUMIFS(Données!$P$2:$P$8815,Données!$D$2:$D$8815,IF(Dashboard!$D$6="(Tous)","*",Dashboard!$D$6),Données!$E$2:$E$8815,IF(Dashboard!$D$7="(Tous)","*",Dashboard!$D$7),Données!$L$2:$L$8815,IF(Dashboard!$D$8="(Tous)","*",Dashboard!$D$8),Données!$D$2:$D$8815,"Lomé") -> 172718.67 | U11: =SUMIFS(Données!$R$2:$R$8815,Données!$D$2:$D$8815,IF(Dashboard!$D$6="(Tous)","*",Dashboard!$D$6),Données!$E$2:$E$8815,IF(Dashboard!$D$7="(Tous)","*",Dashboard!$D$7),Données!$L$2:$L$8815,IF(Dashboard!$D$8="(Tous)","*",Dashboard!$D$8),Données!$D$2:$D$8815,"Lomé") -> 47089.029 | V11: =IFERROR(COUNTIFS(Données!$D$2:$D$8815,IF(Dashboard!$D$6="(Tous)","*",Dashboard!$D$6),Données!$E$2:$E$8815,IF(Dashboard!$D$7="(Tous)","*",Dashboard!$D$7),Données!$L$2:$L$8815,IF(Dashboard!$D$8="(Tous)","*",Dashboard!$D$8),Données!$D$2:$D$8815,"Lomé",Données!$N$2:$N$8815,"Annulée")/COUNTIFS(Données!$D$2:$D$8815,IF(Dashboard!$D$6="(Tous)","*",Dashboard!$D$6),Données!$E$2:$E$8815,IF(Dashboard!$D$7="(Tous)","*",Dashboard!$D$7),Données!$L$2:$L$8815,IF(Dashboard!$D$8="(Tous)","*",Dashboard!$D$8),Données!$D$2:$D$8815,"Lomé"),0) -> 0
C12: Chiffre d'affaires total | F12: Profit net estimé | I12: Panier moyen | S12: Cotonou | T12: =SUMIFS(Données!$P$2:$P$8815,Données!$D$2:$D$8815,IF(Dashboard!$D$6="(Tous)","*",Dashboard!$D$6),Données!$E$2:$E$8815,IF(Dashboard!$D$7="(Tous)","*",Dashboard!$D$7),Données!$L$2:$L$8815,IF(Dashboard!$D$8="(Tous)","*",Dashboard!$D$8),Données!$D$2:$D$8815,"Cotonou") -> 147718.07 | U12: =SUMIFS(Données!$R$2:$R$8815,Données!$D$2:$D$8815,IF(Dashboard!$D$6="(Tous)","*",Dashboard!$D$6),Données!$E$2:$E$8815,IF(Dashboard!$D$7="(Tous)","*",Dashboard!$D$7),Données!$L$2:$L$8815,IF(Dashboard!$D$8="(Tous)","*",Dashboard!$D$8),Données!$D$2:$D$8815,"Cotonou") -> 41150.218 | V12: =IFERROR(COUNTIFS(Données!$D$2:$D$8815,IF(Dashboard!$D$6="(Tous)","*",Dashboard!$D$6),Données!$E$2:$E$8815,IF(Dashboard!$D$7="(Tous)","*",Dashboard!$D$7),Données!$L$2:$L$8815,IF(Dashboard!$D$8="(Tous)","*",Dashboard!$D$8),Données!$D$2:$D$8815,"Cotonou",Données!$N$2:$N$8815,"Annulée")/COUNTIFS(Données!$D$2:$D$8815,IF(Dashboard!$D$6="(Tous)","*",Dashboard!$D$6),Données!$E$2:$E$8815,IF(Dashboard!$D$7="(Tous)","*",Dashboard!$D$7),Données!$L$2:$L$8815,IF(Dashboard!$D$8="(Tous)","*",Dashboard!$D$8),Données!$D$2:$D$8815,"Cotonou"),0) -> 0
O13: Mois | P13: CA | S13: Libreville | T13: =SUMIFS(Données!$P$2:$P$8815,Données!$D$2:$D$8815,IF(Dashboard!$D$6="(Tous)","*",Dashboard!$D$6),Données!$E$2:$E$8815,IF(Dashboard!$D$7="(Tous)","*",Dashboard!$D$7),Données!$L$2:$L$8815,IF(Dashboard!$D$8="(Tous)","*",Dashboard!$D$8),Données!$D$2:$D$8815,"Libreville") -> 115438.64 | U13: =SUMIFS(Données!$R$2:$R$8815,Données!$D$2:$D$8815,IF(Dashboard!$D$6="(Tous)","*",Dashboard!$D$6),Données!$E$2:$E$8815,IF(Dashboard!$D$7="(Tous)","*",Dashboard!$D$7),Données!$L$2:$L$8815,IF(Dashboard!$D$8="(Tous)","*",Dashboard!$D$8),Données!$D$2:$D$8815,"Libreville") -> 32656.876 | V13: =IFERROR(COUNTIFS(Données!$D$2:$D$8815,IF(Dashboard!$D$6="(Tous)","*",Dashboard!$D$6),Données!$E$2:$E$8815,IF(Dashboard!$D$7="(Tous)","*",Dashboard!$D$7),Données!$L$2:$L$8815,IF(Dashboard!$D$8="(Tous)","*",Dashboard!$D$8),Données!$D$2:$D$8815,"Libreville",Données!$N$2:$N$8815,"Annulée")/COUNTIFS(Données!$D$2:$D$8815,IF(Dashboard!$D$6="(Tous)","*",Dashboard!$D$6),Données!$E$2:$E$8815,IF(Dashboard!$D$7="(Tous)","*",Dashboard!$D$7),Données!$L$2:$L$8815,IF(Dashboard!$D$8="(Tous)","*",Dashboard!$D$8),Données!$D$2:$D$8815,"Libreville"),0) -> 0
C14: =COUNTIFS(Données!$D$2:$D$8815,IF(Dashboard!$D$6="(Tous)","*",Dashboard!$D$6),Données!$E$2:$E$8815,IF(Dashboard!$D$7="(Tous)","*",Dashboard!$D$7),Données!$L$2:$L$8815,IF(Dashboard!$D$8="(Tous)","*",Dashboard!$D$8)) -> 8814 | F14: =IFERROR(COUNTIFS(Données!$D$2:$D$8815,IF(Dashboard!$D$6="(Tous)","*",Dashboard!$D$6),Données!$E$2:$E$8815,IF(Dashboard!$D$7="(Tous)","*",Dashboard!$D$7),Données!$L$2:$L$8815,IF(Dashboard!$D$8="(Tous)","*",Dashboard!$D$8),Données!$N$2:$N$8815,"Retournée")/COUNTIFS(Données!$D$2:$D$8815,IF(Dashboard!$D$6="(Tous)","*",Dashboard!$D$6),Données!$E$2:$E$8815,IF(Dashboard!$D$7="(Tous)","*",Dashboard!$D$7),Données!$L$2:$L$8815,IF(Dashboard!$D$8="(Tous)","*",Dashboard!$D$8)),0) -> 0.081688223 | I14: =IFERROR(COUNTIFS(Données!$D$2:$D$8815,IF(Dashboard!$D$6="(Tous)","*",Dashboard!$D$6),Données!$E$2:$E$8815,IF(Dashboard!$D$7="(Tous)","*",Dashboard!$D$7),Données!$L$2:$L$8815,IF(Dashboard!$D$8="(Tous)","*",Dashboard!$D$8),Données!$N$2:$N$8815,"Annulée")/COUNTIFS(Données!$D$2:$D$8815,IF(Dashboard!$D$6="(Tous)","*",Dashboard!$D$6),Données!$E$2:$E$8815,IF(Dashboard!$D$7="(Tous)","*",Dashboard!$D$7),Données!$L$2:$L$8815,IF(Dashboard!$D$8="(Tous)","*",Dashboard!$D$8)),0) -> 0.019400953 | O14: Juillet | P14: =SUMIFS(Données!$P$2:$P$8815,Données!$D$2:$D$8815,IF(Dashboard!$D$6="(Tous)","*",Dashboard!$D$6),Données!$E$2:$E$8815,IF(Dashboard!$D$7="(Tous)","*",Dashboard!$D$7),Données!$L$2:$L$8815,IF(Dashboard!$D$8="(Tous)","*",Dashboard!$D$8),Données!$S$2:$S$8815,"July") -> 372969.7 | S14: Brazzaville | T14: =SUMIFS(Données!$P$2:$P$8815,Données!$D$2:$D$8815,IF(Dashboard!$D$6="(Tous)","*",Dashboard!$D$6),Données!$E$2:$E$8815,IF(Dashboard!$D$7="(Tous)","*",Dashboard!$D$7),Données!$L$2:$L$8815,IF(Dashboard!$D$8="(Tous)","*",Dashboard!$D$8),Données!$D$2:$D$8815,"Brazzaville") -> 100743.52 | U14: =SUMIFS(Données!$R$2:$R$8815,Données!$D$2:$D$8815,IF(Dashboard!$D$6="(Tous)","*",Dashboard!$D$6),Données!$E$2:$E$8815,IF(Dashboard!$D$7="(Tous)","*",Dashboard!$D$7),Données!$L$2:$L$8815,IF(Dashboard!$D$8="(Tous)","*",Dashboard!$D$8),Données!$D$2:$D$8815,"Brazzaville") -> 27425.427 | V14: =IFERROR(COUNTIFS(Données!$D$2:$D$8815,IF(Dashboard!$D$6="(Tous)","*",Dashboard!$D$6),Données!$E$2:$E$8815,IF(Dashboard!$D$7="(Tous)","*",Dashboard!$D$7),Données!$L$2:$L$8815,IF(Dashboard!$D$8="(Tous)","*",Dashboard!$D$8),Données!$D$2:$D$8815,"Brazzaville",Données!$N$2:$N$8815,"Annulée")/COUNTIFS(Données!$D$2:$D$8815,IF(Dashboard!$D$6="(Tous)","*",Dashboard!$D$6),Données!$E$2:$E$8815,IF(Dashboard!$D$7="(Tous)","*",Dashboard!$D$7),Données!$L$2:$L$8815,IF(Dashboard!$D$8="(Tous)","*",Dashboard!$D$8),Données!$D$2:$D$8815,"Brazzaville"),0) -> 0
O15: Août | P15: =SUMIFS(Données!$P$2:$P$8815,Données!$D$2:$D$8815,IF(Dashboard!$D$6="(Tous)","*",Dashboard!$D$6),Données!$E$2:$E$8815,IF(Dashboard!$D$7="(Tous)","*",Dashboard!$D$7),Données!$L$2:$L$8815,IF(Dashboard!$D$8="(Tous)","*",Dashboard!$D$8),Données!$S$2:$S$8815,"August") -> 416284.95
C16: Nb commandes | F16: Taux de retour | I16: Taux d'annulation | O16: Septembre | P16: =SUMIFS(Données!$P$2:$P$8815,Données!$D$2:$D$8815,IF(Dashboard!$D$6="(Tous)","*",Dashboard!$D$6),Données!$E$2:$E$8815,IF(Dashboard!$D$7="(Tous)","*",Dashboard!$D$7),Données!$L$2:$L$8815,IF(Dashboard!$D$8="(Tous)","*",Dashboard!$D$8),Données!$S$2:$S$8815,"September") -> 374747.73
O17: Octobre | P17: =SUMIFS(Données!$P$2:$P$8815,Données!$D$2:$D$8815,IF(Dashboard!$D$6="(Tous)","*",Dashboard!$D$6),Données!$E$2:$E$8815,IF(Dashboard!$D$7="(Tous)","*",Dashboard!$D$7),Données!$L$2:$L$8815,IF(Dashboard!$D$8="(Tous)","*",Dashboard!$D$8),Données!$S$2:$S$8815,"October") -> 415787.71
O18: Novembre | P18: =SUMIFS(Données!$P$2:$P$8815,Données!$D$2:$D$8815,IF(Dashboard!$D$6="(Tous)","*",Dashboard!$D$6),Données!$E$2:$E$8815,IF(Dashboard!$D$7="(Tous)","*",Dashboard!$D$7),Données!$L$2:$L$8815,IF(Dashboard!$D$8="(Tous)","*",Dashboard!$D$8),Données!$S$2:$S$8815,"November") -> 365790.12
O19: Décembre | P19: =SUMIFS(Données!$P$2:$P$8815,Données!$D$2:$D$8815,IF(Dashboard!$D$6="(Tous)","*",Dashboard!$D$6),Données!$E$2:$E$8815,IF(Dashboard!$D$7="(Tous)","*",Dashboard!$D$7),Données!$L$2:$L$8815,IF(Dashboard!$D$8="(Tous)","*",Dashboard!$D$8),Données!$S$2:$S$8815,"December") -> 439312.36

Sheet Marketing & Clients
A1: AfriMarket - Marketing & Clients
A3: ROI, rétention, segmentation RFM et concentration de la valeur client
A5: Le ROI par canal respecte les filtres Ville/Catégorie/Canal de la page "Dashboard". La rétention, la segmentation et le Pareto sont calculés au niveau client, sur l'ensemble de la base (non filtrables par ville/catégorie). | N5: Canal | O5: ROI | R5: Segment | S5: Nb clients | T5: CA
N6: Instagram Ads | O6: =IFERROR(((SUMIFS(Données!$P$2:$P$8815,Données!$D$2:$D$8815,IF(Dashboard!$D$6="(Tous)","*",Dashboard!$D$6),Données!$E$2:$E$8815,IF(Dashboard!$D$7="(Tous)","*",Dashboard!$D$7),Données!$L$2:$L$8815,IF(Dashboard!$D$8="(Tous)","*",Dashboard!$D$8),Données!$L$2:$L$8815,"Instagram Ads",Données!$N$2:$N$8815,"Livrée")+SUMIFS(Données!$P$2:$P$8815,Données!$D$2:$D$8815,IF(Dashboard!$D$6="(Tous)","*",Dashboard!$D$6),Données!$E$2:$E$8815,IF(Dashboard!$D$7="(Tous)","*",Dashboard!$D$7),Données!$L$2:$L$8815,IF(Dashboard!$D$8="(Tous)","*",Dashboard!$D$8),Données!$L$2:$L$8815,"Instagram Ads",Données!$N$2:$N$8815,"Retournée"))-(SUMIFS(Données!$M$2:$M$8815,Données!$D$2:$D$8815,IF(Dashboard!$D$6="(Tous)","*",Dashboard!$D$6),Données!$E$2:$E$8815,IF(Dashboard!$D$7="(Tous)","*",Dashboard!$D$7),Données!$L$2:$L$8815,IF(Dashboard!$D$8="(Tous)","*",Dashboard!$D$8),Données!$L$2:$L$8815,"Instagram Ads",Données!$N$2:$N$8815,"Livrée")+SUMIFS(Données!$M$2:$M$8815,Données!$D$2:$D$8815,IF(Dashboard!$D$6="(Tous)","*",Dashboard!$D$6),Données!$E$2:$E$8815,IF(Dashboard!$D$7="(Tous)","*",Dashboard!$D$7),Données!$L$2:$L$8815,IF(Dashboard!$D$8="(Tous)","*",Dashboard!$D$8),Données!$L$2:$L$8815,"Instagram Ads",Données!$N$2:$N$8815,"Retournée")))/(SUMIFS(Données!$M$2:$M$8815,Données!$D$2:$D$8815,IF(Dashboard!$D$6="(Tous)","*",Dashboard!$D$6),Données!$E$2:$E$8815,IF(Dashboard!$D$7="(Tous)","*",Dashboard!$D$7),Données!$L$2:$L$8815,IF(Dashboard!$D$8="(Tous)","*",Dashboard!$D$8),Données!$L$2:$L$8815,"Instagram Ads",Données!$N$2:$N$8815,"Livrée")+SUMIFS(Données!$M$2:$M$8815,Données!$D$2:$D$8815,IF(Dashboard!$D$6="(Tous)","*",Dashboard!$D$6),Données!$E$2:$E$8815,IF(Dashboard!$D$7="(Tous)","*",Dashboard!$D$7),Données!$L$2:$L$8815,IF(Dashboard!$D$8="(Tous)","*",Dashboard!$D$8),Données!$L$2:$L$8815,"Instagram Ads",Données!$N$2:$N$8815,"Retournée")),0) -> 24.639157 | R6: Occasionnels | S6: =COUNTIFS('Segments clients'!$I$2:$I$1708,"Occasionnels") -> 312 | T6: =SUMIFS('Segments clients'!$D$2:$D$1708,'Segments clients'!$I$2:$I$1708,"Occasionnels") -> 98584.715
N7: Google Ads | O7: =IFERROR(((SUMIFS(Données!$P$2:$P$8815,Données!$D$2:$D$8815,IF(Dashboard!$D$6="(Tous)","*",Dashboard!$D$6),Données!$E$2:$E$8815,IF(Dashboard!$D$7="(Tous)","*",Dashboard!$D$7),Données!$L$2:$L$8815,IF(Dashboard!$D$8="(Tous)","*",Dashboard!$D$8),Données!$L$2:$L$8815,"Google Ads",Données!$N$2:$N$8815,"Livrée")+SUMIFS(Données!$P$2:$P$8815,Données!$D$2:$D$8815,IF(Dashboard!$D$6="(Tous)","*",Dashboard!$D$6),Données!$E$2:$E$8815,IF(Dashboard!$D$7="(Tous)","*",Dashboard!$D$7),Données!$L$2:$L$8815,IF(Dashboard!$D$8="(Tous)","*",Dashboard!$D$8),Données!$L$2:$L$8815,"Google Ads",Données!$N$2:$N$8815,"Retournée"))-(SUMIFS(Données!$M$2:$M$8815,Données!$D$2:$D$8815,IF(Dashboard!$D$6="(Tous)","*",Dashboard!$D$6),Données!$E$2:$E$8815,IF(Dashboard!$D$7="(Tous)","*",Dashboard!$D$7),Données!$L$2:$L$8815,IF(Dashboard!$D$8="(Tous)","*",Dashboard!$D$8),Données!$L$2:$L$8815,"Google Ads",Données!$N$2:$N$8815,"Livrée")+SUMIFS(Données!$M$2:$M$8815,Données!$D$2:$D$8815,IF(Dashboard!$D$6="(Tous)","*",Dashboard!$D$6),Données!$E$2:$E$8815,IF(Dashboard!$D$7="(Tous)","*",Dashboard!$D$7),Données!$L$2:$L$8815,IF(Dashboard!$D$8="(Tous)","*",Dashboard!$D$8),Données!$L$2:$L$8815,"Google Ads",Données!$N$2:$N$8815,"Retournée")))/(SUMIFS(Données!$M$2:$M$8815,Données!$D$2:$D$8815,IF(Dashboard!$D$6="(Tous)","*",Dashboard!$D$6),Données!$E$2:$E$8815,IF(Dashboard!$D$7="(Tous)","*",Dashboard!$D$7),Données!$L$2:$L$8815,IF(Dashboard!$D$8="(Tous)","*",Dashboard!$D$8),Données!$L$2:$L$8815,"Google Ads",Données!$N$2:$N$8815,"Livrée")+SUMIFS(Données!$M$2:$M$8815,Données!$D$2:$D$8815,IF(Dashboard!$D$6="(Tous)","*",Dashboard!$D$6),Données!$E$2:$E$8815,IF(Dashboard!$D$7="(Tous)","*",Dashboard!$D$7),Données!$L$2:$L$8815,IF(Dashboard!$D$8="(Tous)","*",Dashboard!$D$8),Données!$L$2:$L$8815,"Google Ads",Données!$N$2:$N$8815,"Retournée")),0) -> 50.034187 | R7: À réactiver | S7: =COUNTIFS('Segments clients'!$I$2:$I$1708,"À réactiver") -> 597 | T7: =SUMIFS('Segments clients'!$D$2:$D$1708,'Segments clients'!$I$2:$I$1708,"À réactiver") -> 211574.9
N8: Email | O8: =IFERROR(((SUMIFS(Données!$P$2:$P$8815,Données!$D$2:$D$8815,IF(Dashboard!$D$6="(Tous)","*",Dashboard!$D$6),Données!$E$2:$E$8815,IF(Dashboard!$D$7="(Tous)","*",Dashboard!$D$7),Données!$L$2:$L$8815,IF(Dashboard!$D$8="(Tous)","*",Dashboard!$D$8),Données!$L$2:$L$8815,"Email",Données!$N$2:$N$8815,"Livrée")+SUMIFS(Données!$P$2:$P$8815,Données!$D$2:$D$8815,IF(Dashboard!$D$6="(Tous)","*",Dashboard!$D$6),Données!$E$2:$E$8815,IF(Dashboard!$D$7="(Tous)","*",Dashboard!$D$7),Données!$L$2:$L$8815,IF(Dashboard!$D$8="(Tous)","*",Dashboard!$D$8),Données!$L$2:$L$8815,"Email",Données!$N$2:$N$8815,"Retournée"))-(SUMIFS(Données!$M$2:$M$8815,Données!$D$2:$D$8815,IF(Dashboard!$D$6="(Tous)","*",Dashboard!$D$6),Données!$E$2:$E$8815,IF(Dashboard!$D$7="(Tous)","*",Dashboard!$D$7),Données!$L$2:$L$8815,IF(Dashboard!$D$8="(Tous)","*",Dashboard!$D$8),Données!$L$2:$L$8815,"Email",Données!$N$2:$N$8815,"Livrée")+SUMIFS(Données!$M$2:$M$8815,Données!$D$2:$D$8815,IF(Dashboard!$D$6="(Tous)","*",Dashboard!$D$6),Données!$E$2:$E$8815,IF(Dashboard!$D$7="(Tous)","*",Dashboard!$D$7),Données!$L$2:$L$8815,IF(Dashboard!$D$8="(Tous)","*",Dashboard!$D$8),Données!$L$2:$L$8815,"Email",Données!$N$2:$N$8815,"Retournée")))/(SUMIFS(Données!$M$2:$M$8815,Données!$D$2:$D$8815,IF(Dashboard!$D$6="(Tous)","*",Dashboard!$D$6),Données!$E$2:$E$8815,IF(Dashboard!$D$7="(Tous)","*",Dashboard!$D$7),Données!$L$2:$L$8815,IF(Dashboard!$D$8="(Tous)","*",Dashboard!$D$8),Données!$L$2:$L$8815,"Email",Données!$N$2:$N$8815,"Livrée")+SUMIFS(Données!$M$2:$M$8815,Données!$D$2:$D$8815,IF(Dashboard!$D$6="(Tous)","*",Dashboard!$D$6),Données!$E$2:$E$8815,IF(Dashboard!$D$7="(Tous)","*",Dashboard!$D$7),Données!$L$2:$L$8815,IF(Dashboard!$D$8="(Tous)","*",Dashboard!$D$8),Données!$L$2:$L$8815,"Email",Données!$N$2:$N$8815,"Retournée")),0) -> 231.45705 | R8: Fidèles | S8: =COUNTIFS('Segments clients'!$I$2:$I$1708,"Fidèles") -> 323 | T8: =SUMIFS('Segments clients'!$D$2:$D$1708,'Segments clients'!$I$2:$I$1708,"Fidèles") -> 317236.44
B9: =SUMPRODUCT(--('Segments clients'!$O$2:$O$1708<0.8))+1 -> 547 | F9: Top 10 clients | N9: Influenceur | O9: =IFERROR(((SUMIFS(Données!$P$2:$P$8815,Données!$D$2:$D$8815,IF(Dashboard!$D$6="(Tous)","*",Dashboard!$D$6),Données!$E$2:$E$8815,IF(Dashboard!$D$7="(Tous)","*",Dashboard!$D$7),Données!$L$2:$L$8815,IF(Dashboard!$D$8="(Tous)","*",Dashboard!$D$8),Données!$L$2:$L$8815,"Influenceur",Données!$N$2:$N$8815,"Livrée")+SUMIFS(Données!$P$2:$P$8815,Données!$D$2:$D$8815,IF(Dashboard!$D$6="(Tous)","*",Dashboard!$D$6),Données!$E$2:$E$8815,IF(Dashboard!$D$7="(Tous)","*",Dashboard!$D$7),Données!$L$2:$L$8815,IF(Dashboard!$D$8="(Tous)","*",Dashboard!$D$8),Données!$L$2:$L$8815,"Influenceur",Données!$N$2:$N$8815,"Retournée"))-(SUMIFS(Données!$M$2:$M$8815,Données!$D$2:$D$8815,IF(Dashboard!$D$6="(Tous)","*",Dashboard!$D$6),Données!$E$2:$E$8815,IF(Dashboard!$D$7="(Tous)","*",Dashboard!$D$7),Données!$L$2:$L$8815,IF(Dashboard!$D$8="(Tous)","*",Dashboard!$D$8),Données!$L$2:$L$8815,"Influenceur",Données!$N$2:$N$8815,"Livrée")+SUMIFS(Données!$M$2:$M$8815,Données!$D$2:$D$8815,IF(Dashboard!$D$6="(Tous)","*",Dashboard!$D$6),Données!$E$2:$E$8815,IF(Dashboard!$D$7="(Tous)","*",Dashboard!$D$7),Données!$L$2:$L$8815,IF(Dashboard!$D$8="(Tous)","*",Dashboard!$D$8),Données!$L$2:$L$8815,"Influenceur",Données!$N$2:$N$8815,"Retournée")))/(SUMIFS(Données!$M$2:$M$8815,Données!$D$2:$D$8815,IF(Dashboard!$D$6="(Tous)","*",Dashboard!$D$6),Données!$E$2:$E$8815,IF(Dashboard!$D$7="(Tous)","*",Dashboard!$D$7),Données!$L$2:$L$8815,IF(Dashboard!$D$8="(Tous)","*",Dashboard!$D$8),Données!$L$2:$L$8815,"Influenceur",Données!$N$2:$N$8815,"Livrée")+SUMIFS(Données!$M$2:$M$8815,Données!$D$2:$D$8815,IF(Dashboard!$D$6="(Tous)","*",Dashboard!$D$6),Données!$E$2:$E$8815,IF(Dashboard!$D$7="(Tous)","*",Dashboard!$D$7),Données!$L$2:$L$8815,IF(Dashboard!$D$8="(Tous)","*",Dashboard!$D$8),Données!$L$2:$L$8815,"Influenceur",Données!$N$2:$N$8815,"Retournée")),0) -> 21.041183 | R9: VIP | S9: =COUNTIFS('Segments clients'!$I$2:$I$1708,"VIP") -> 475 | T9: =SUMIFS('Segments clients'!$D$2:$D$1708,'Segments clients'!$I$2:$I$1708,"VIP") -> 1709991.2
F10: Rang | G10: Client | H10: CA
B11: clients nécessaires pour 80% du CA (loi de Pareto) | F11: 1 | G11: =INDEX('Segments clients'!$A$2:$A$1708,MATCH(H11,'Segments clients'!$D$2:$D$1708,0)) -> C0157 | H11: =LARGE('Segments clients'!$D$2:$D$1708,F11) -> 11553.739
F12: 2 | G12: =INDEX('Segments clients'!$A$2:$A$1708,MATCH(H12,'Segments clients'!$D$2:$D$1708,0)) -> C0266 | H12: =LARGE('Segments clients'!$D$2:$D$1708,F12) -> 10673.227 | N12: Canal | O12: Taux de rétention | R12: % clients | S12: % CA cumulé
F13: 3 | G13: =INDEX('Segments clients'!$A$2:$A$1708,MATCH(H13,'Segments clients'!$D$2:$D$1708,0)) -> C0120 | H13: =LARGE('Segments clients'!$D$2:$D$1708,F13) -> 9240.3449 | N13: Instagram Ads | O13: =IFERROR(COUNTIFS('Segments clients'!$J$2:$J$1708,"Instagram Ads",'Segments clients'!$K$2:$K$1708,1)/COUNTIFS('Segments clients'!$J$2:$J$1708,"Instagram Ads"),0) -> 0.69683258 | R13: 10 | S13: =IFERROR(SUMIFS('Segments clients'!$D$2:$D$1708,'Segments clients'!$M$2:$M$1708,"<="&ROUND(1707*1/10,0))/SUM('Segments clients'!$D$2:$D$1708),0) -> 0.40380997
F14: 4 | G14: =INDEX('Segments clients'!$A$2:$A$1708,MATCH(H14,'Segments clients'!$D$2:$D$1708,0)) -> C0114 | H14: =LARGE('Segments clients'!$D$2:$D$1708,F14) -> 8915.4355 | N14: Google Ads | O14: =IFERROR(COUNTIFS('Segments clients'!$J$2:$J$1708,"Google Ads",'Segments clients'!$K$2:$K$1708,1)/COUNTIFS('Segments clients'!$J$2:$J$1708,"Google Ads"),0) -> 0.7409201 | R14: 20 | S14: =IFERROR(SUMIFS('Segments clients'!$D$2:$D$1708,'Segments clients'!$M$2:$M$1708,"<="&ROUND(1707*2/10,0))/SUM('Segments clients'!$D$2:$D$1708),0) -> 0.63757736
F15: 5 | G15: =INDEX('Segments clients'!$A$2:$A$1708,MATCH(H15,'Segments clients'!$D$2:$D$1708,0)) -> C0051 | H15: =LARGE('Segments clients'!$D$2:$D$1708,F15) -> 8646.399 | N15: Email | O15: =IFERROR(COUNTIFS('Segments clients'!$J$2:$J$1708,"Email",'Segments clients'!$K$2:$K$1708,1)/COUNTIFS('Segments clients'!$J$2:$J$1708,"Email"),0) -> 0.69252078 | R15: 30 | S15: =IFERROR(SUMIFS('Segments clients'!$D$2:$D$1708,'Segments clients'!$M$2:$M$1708,"<="&ROUND(1707*3/10,0))/SUM('Segments clients'!$D$2:$D$1708),0) -> 0.77914955
F16: 6 | G16: =INDEX('Segments clients'!$A$2:$A$1708,MATCH(H16,'Segments clients'!$D$2:$D$1708,0)) -> C0067 | H16: =LARGE('Segments clients'!$D$2:$D$1708,F16) -> 8476.4071 | N16: Influenceur | O16: =IFERROR(COUNTIFS('Segments clients'!$J$2:$J$1708,"Influenceur",'Segments clients'!$K$2:$K$1708,1)/COUNTIFS('Segments clients'!$J$2:$J$1708,"Influenceur"),0) -> 0.74814815 | R16: 40 | S16: =IFERROR(SUMIFS('Segments clients'!$D$2:$D$1708,'Segments clients'!$M$2:$M$1708,"<="&ROUND(1707*4/10,0))/SUM('Segments clients'!$D$2:$D$1708),0) -> 0.86599525
F17: 7 | G17: =INDEX('Segments clients'!$A$2:$A$1708,MATCH(H17,'Segments clients'!$D$2:$D$1708,0)) -> C0003 | H17: =LARGE('Segments clients'!$D$2:$D$1708,F17) -> 8437.1465 | R17: 50 | S17: =IFERROR(SUMIFS('Segments clients'!$D$2:$D$1708,'Segments clients'!$M$2:$M$1708,"<="&ROUND(1707*5/10,0))/SUM('Segments clients'!$D$2:$D$1708),0) -> 0.92246186
F18: 8 | G18: =INDEX('Segments clients'!$A$2:$A$1708,MATCH(H18,'Segments clients'!$D$2:$D$1708,0)) -> C0364 | H18: =LARGE('Segments clients'!$D$2:$D$1708,F18) -> 8252.4673 | R18: 60 | S18: =IFERROR(SUMIFS('Segments clients'!$D$2:$D$1708,'Segments clients'!$M$2:$M$1708,"<="&ROUND(1707*6/10,0))/SUM('Segments clients'!$D$2:$D$1708),0) -> 0.9573811
F19: 9 | G19: =INDEX('Segments clients'!$A$2:$A$1708,MATCH(H19,'Segments clients'!$D$2:$D$1708,0)) -> C0054 | H19: =LARGE('Segments clients'!$D$2:$D$1708,F19) -> 8044.1152 | R19: 70 | S19: =IFERROR(SUMIFS('Segments clients'!$D$2:$D$1708,'Segments clients'!$M$2:$M$1708,"<="&ROUND(1707*7/10,0))/SUM('Segments clients'!$D$2:$D$1708),0) -> 0.97894103
F20: 10 | G20: =INDEX('Segments clients'!$A$2:$A$1708,MATCH(H20,'Segments clients'!$D$2:$D$1708,0)) -> C0379 | H20: =LARGE('Segments clients'!$D$2:$D$1708,F20) -> 7948.451 | R20: 80 | S20: =IFERROR(SUMIFS('Segments clients'!$D$2:$D$1708,'Segments clients'!$M$2:$M$1708,"<="&ROUND(1707*8/10,0))/SUM('Segments clients'!$D$2:$D$1708),0) -> 0.99080917
R21: 90 | S21: =IFERROR(SUMIFS('Segments clients'!$D$2:$D$1708,'Segments clients'!$M$2:$M$1708,"<="&ROUND(1707*9/10,0))/SUM('Segments clients'!$D$2:$D$1708),0) -> 0.99732344
R22: 100 | S22: =IFERROR(SUMIFS('Segments clients'!$D$2:$D$1708,'Segments clients'!$M$2:$M$1708,"<="&ROUND(1707*10/10,0))/SUM('Segments clients'!$D$2:$D$1708),0) -> 1

Sheet Données
A1: id_commande | B1: date_commande | C1: id_client | D1: ville | E1: categorie | F1: nom_produit | G1: prix_unitaire | H1: quantite | I1: remise | J1: cout_livraison | K1: methode_paiement | L1: canal_marketing | M1: cout_marketing | N1: statut_commande | O1: remise_negative | P1: CA | Q1: Marge_Brute | R1: profit_net | S1: mois | T1: indicateur_retour | U1: indicateur_annulation | V1: nombre_commandes_par_client | W1: valeur_vie_client
A2: CMD100000 | B2: 2025-12-11 | C2: C0379 | D2: Brazzaville | E2: Mode | F2: Produit_Mode_9 | G2: 49.72 | H2: 3 | I2: 0.07 | J2: 2.45 | K2: Mobile Money | L2: Email | M2: 1 | N2: Livrée | O2: FALSE | P2: 138.7188 | Q2: 49.2228 | R2: 45.7728 | S2: December | T2: 0 | U2: 0 | V2: 23 | W2: 2212.105
A3: CMD100001 | B3: 2025-07-27 | C3: C1827 | D3: Libreville | E3: Beaute | F3: Produit_Beauté_3 | G3: 37.18 | H3: 2 | I3: 0.1 | J3: 6.89 | K3: Paiement à la livraison | L3: Instagram Ads | M3: 8.04 | N3: Livrée | O3: FALSE | P3: 66.924 | Q3: 22.308 | R3: 7.378 | S3: July | T3: 0 | U3: 0 | V3: 4 | W3: 151.5668
A4: CMD100004 | B4: 2025-11-28 | C4: C0003 | D4: Libreville | E4: Electronique | F4: Produit_Électronique_45 | G4: 498.71 | H4: 2 | I4: 0.02 | J4: 5.16 | K4: Mobile Money | L4: Email | M4: 0.55 | N4: Livrée | O4: FALSE | P4: 977.4716 | Q4: 379.0196 | R4: 373.3096 | S4: November | T4: 0 | U4: 0 | V4: 25 | W4: 2626.2725
A5: CMD100005 | B5: 2025-10-17 | C5: C0079 | D5: Dakar | E5: Maison | F5: Produit_Maison_7 | G5: 71.17 | H5: 3 | I5: 0.1 | J5: 8.63 | K5: Virement | L5: Instagram Ads | M5: 5.45 | N5: Livrée | O5: FALSE | P5: 192.159 | Q5: 64.053 | R5: 49.973 | S5: October | T5: 0 | U5: 0 | V5: 16 | W5: 909.716
A6: CMD100006 | B6: 2025-07-24 | C6: C0183 | D6: Abidjan | E6: Mode | F6: Produit_Mode_3 | G6: 23.04 | H6: 3 | I6: 0.1 | J6: 3.59 | K6: Virement | L6: Instagram Ads | M6: 9.23 | N6: Livrée | O6: TRUE | P6: 62.208 | Q6: 20.736 | R6: 7.916 | S6: July | T6: 0 | U6: 0 | V6: 14 | W6: 687.7705
A7: CMD100007 | B7: 2025-10-26 | C7: C0193 | D7: Lomé | E7: Beaute | F7: Produit_Beauté_41 | G7: 26.08 | H7: 3 | I7: 0.14 | J7: 2.51 | K7: Virement | L7: Instagram Ads | M7: 6.16 | N7: Livrée | O7: FALSE | P7: 67.2864 | Q7: 20.3424 | R7: 11.6724 | S7: October | T7: 0 | U7: 0 | V7: 20 | W7: 1794.1579
A8: CMD100008 | B8: 2025-12-06 | C8: C0740 | D8: Abidjan | E8: Mode | F8: Produit_Mode_3 | G8: 52.19 | H8: 3 | I8: 0.15 | J8: 4.05 | K8: Carte | L8: Email | M8: 1.77 | N8: Livrée | O8: FALSE | P8: 133.0845 | Q8: 39.1425 | R8: 33.3225 | S8: December | T8: 0 | U8: 0 | V8: 3 | W8: 119.477
A9: CMD100009 | B9: 2025-12-17 | C9: C0148 | D9: Dakar | E9: Electronique | F9: Produit_Électronique_7 | G9: 562.75 | H9: 2 | I9: 0.08 | J9: 9.26 | K9: Mobile Money | L9: Instagram Ads | M9: 5.31 | N9: Livrée | O9: FALSE | P9: 1035.46 | Q9: 360.16 | R9: 345.59 | S9: December | T9: 0 | U9: 0 | V9: 18 | W9: 839.6126
A10: CMD100010 | B10: 2025-10-06 | C10: C0325 | D10: Abidjan | E10: Electronique | F10: Produit_Électronique_24 | G10: 305.29 | H10: 3 | I10: 0.09 | J10: 8.43 | K10: Mobile Money | L10: Instagram Ads | M10: 14.3 | N10: Livrée | O10: FALSE | P10: 833.4417 | Q10: 283.9197 | R10: 261.1897 | S10: October | T10: 0 | U10: 0 | V10: 14 | W10: 711.6688
A11: CMD100011 | B11: 2025-09-29 | C11: C0136 | D11: Cotonou | E11: Electronique | F11: Produit_Électronique_39 | G11: 489.25 | H11: 3 | I11: 0.08 | J11: 2 | K11: Carte | L11: Instagram Ads | M11: 8.56 | N11: Livrée | O11: FALSE | P11: 1350.33 | Q11: 469.68 | R11: 459.12 | S11: September | T11: 0 | U11: 0 | V11: 12 | W11: 1206.3514
A12: CMD100012 | B12: 2025-12-10 | C12: C0373 | D12: Abidjan | E12: Mode | F12: Produit_Mode_25 | G12: 41.91 | H12: 2 | I12: 0.08 | J12: 7.62 | K12: Paiement à la livraison | L12: Instagram Ads | M12: 8.38 | N12: Livrée | O12: FALSE | P12: 77.1144 | Q12: 26.8224 | R12: 10.8224 | S12: December | T12: 0 | U12: 0 | V12: 18 | W12: 988.7876
A13: CMD100013 | B13: 2025-09-08 | C13: C1310 | D13: Brazzaville | E13: Mode | F13: Produit_Mode_44 | G13: 21.26 | H13: 2 | I13: 0.23 | J13: 5.29 | K13: Mobile Money | L13: Google Ads | M13: 4.33 | N13: Livrée | O13: FALSE | P13: 32.7404 | Q13: 7.2284 | R13: -2.3916 | S13: September | T13: 0 | U13: 0 | V13: 3 | W13: 4.1222
... A8815: CMD109999 | B8815: 2025-07-23 | C8815: C0251 | D8815: Lomé | E8815: Electronique | F8815: Produit_Électronique_11 | G8815: 577.84 | H8815: 3 | I8815: 0.29 | J8815: 4.15 | K8815: Paiement à la livraison | L8815: Instagram Ads | M8815: 13.76 | N8815: Livrée | O8815: FALSE | P8815: 1230.7992 | Q8815: 190.6872 | R8815: 172.7772 | S8815: July | T8815: 0 | U8815: 0 | V8815: 19 | W8815: 1271.3682

Sheet Segments clients
A1: id_client | B1: recency | C1: frequency | D1: CA | E1: R_score | F1: F_score | G1: M_score | H1: RFM_score | I1: Segment | J1: CanalAcquisition | K1: Recurrent | L1: profit | M1: Rang_CA | N1: CA_cumulee | O1: Pct_cumule_CA
A2: C0000 | B2: 5 | C2: 16 | D2: 4523.1153 | E2: 4 | F2: 4 | G2: 4 | H2: 12 | I2: VIP | J2: Email | K2: 1 | L2: 1103.1713 | M2: =_xlfn.RANK.EQ(D2,'Segments clients'!$D$2:$D$1708,0) -> 127 | N2: =SUMIFS('Segments clients'!$D$2:$D$1708,'Segments clients'!$M$2:$M$1708,"<="&M2) -> 758399.46 | O2: =IFERROR(N2/(SUM('Segments clients'!$D$2:$D$1708)),0) -> 0.32446461
A3: C0001 | B3: 5 | C3: 22 | D3: 6959.438 | E3: 4 | F3: 4 | G3: 4 | H3: 12 | I3: VIP | J3: Instagram Ads | K3: 1 | L3: 1694.472 | M3: =_xlfn.RANK.EQ(D3,'Segments clients'!$D$2:$D$1708,0) -> 25 | N3: =SUMIFS('Segments clients'!$D$2:$D$1708,'Segments clients'!$M$2:$M$1708,"<="&M3) -> 200595.96 | O3: =IFERROR(N3/(SUM('Segments clients'!$D$2:$D$1708)),0) -> 0.085820593
A4: C0002 | B4: 9 | C4: 23 | D4: 7309.1561 | E4: 4 | F4: 4 | G4: 4 | H4: 12 | I4: VIP | J4: Google Ads | K4: 1 | L4: 2031.5921 | M4: =_xlfn.RANK.EQ(D4,'Segments clients'!$D$2:$D$1708,0) -> 18 | N4: =SUMIFS('Segments clients'!$D$2:$D$1708,'Segments clients'!$M$2:$M$1708,"<="&M4) -> 150997.47 | O4: =IFERROR(N4/(SUM('Segments clients'!$D$2:$D$1708)),0) -> 0.064600962
A5: C0003 | B5: 6 | C5: 25 | D5: 8437.1465 | E5: 4 | F5: 4 | G5: 4 | H5: 12 | I5: VIP | J5: Instagram Ads | K5: 1 | L5: 2626.2725 | M5: =_xlfn.RANK.EQ(D5,'Segments clients'!$D$2:$D$1708,0) -> 7 | N5: =SUMIFS('Segments clients'!$D$2:$D$1708,'Segments clients'!$M$2:$M$1708,"<="&M5) -> 65942.699 | O5: =IFERROR(N5/(SUM('Segments clients'!$D$2:$D$1708)),0) -> 0.028212141
A6: C0004 | B6: 41 | C6: 15 | D6: 4543.5824 | E6: 2 | F6: 4 | G6: 4 | H6: 10 | I6: VIP | J6: Email | K6: 1 | L6: 1276.2064 | M6: =_xlfn.RANK.EQ(D6,'Segments clients'!$D$2:$D$1708,0) -> 124 | N6: =SUMIFS('Segments clients'!$D$2:$D$1708,'Segments clients'!$M$2:$M$1708,"<="&M6) -> 744817.67 | O6: =IFERROR(N6/(SUM('Segments clients'!$D$2:$D$1708)),0) -> 0.31865394
A7: C0005 | B7: 7 | C7: 21 | D7: 6773.8798 | E7: 4 | F7: 4 | G7: 4 | H7: 12 | I7: VIP | J7: Google Ads | K7: 1 | L7: 1859.8818 | M7: =_xlfn.RANK.EQ(D7,'Segments clients'!$D$2:$D$1708,0) -> 28 | N7: =SUMIFS('Segments clients'!$D$2:$D$1708,'Segments clients'!$M$2:$M$1708,"<="&M7) -> 221168.11 | O7: =IFERROR(N7/(SUM('Segments clients'!$D$2:$D$1708)),0) -> 0.094621935
A8: C0006 | B8: 16 | C8: 16 | D8: 2125.7175 | E8: 3 | F8: 4 | G8: 4 | H8: 11 | I8: VIP | J8: Instagram Ads | K8: 1 | L8: 483.5955 | M8: =_xlfn.RANK.EQ(D8,'Segments clients'!$D$2:$D$1708,0) -> 397 | N8: =SUMIFS('Segments clients'!$D$2:$D$1708,'Segments clients'!$M$2:$M$1708,"<="&M8) -> 1619957.3 | O8: =IFERROR(N8/(SUM('Segments clients'!$D$2:$D$1708)),0) -> 0.69306327
A9: C0007 | B9: 4 | C9: 14 | D9: 2662.1299 | E9: 4 | F9: 4 | G9: 4 | H9: 12 | I9: VIP | J9: Google Ads | K9: 1 | L9: 525.9819 | M9: =_xlfn.RANK.EQ(D9,'Segments clients'!$D$2:$D$1708,0) -> 320 | N9: =SUMIFS('Segments clients'!$D$2:$D$1708,'Segments clients'!$M$2:$M$1708,"<="&M9) -> 1436145.4 | O9: =IFERROR(N9/(SUM('Segments clients'!$D$2:$D$1708)),0) -> 0.61442337
A10: C0008 | B10: 14 | C10: 13 | D10: 2742.0744 | E10: 3 | F10: 4 | G10: 4 | H10: 11 | I10: VIP | J10: Instagram Ads | K10: 1 | L10: 820.0964 | M10: =_xlfn.RANK.EQ(D10,'Segments clients'!$D$2:$D$1708,0) -> 311 | N10: =SUMIFS('Segments clients'!$D$2:$D$1708,'Segments clients'!$M$2:$M$1708,"<="&M10) -> 1411958.3 | O10: =IFERROR(N10/(SUM('Segments clients'!$D$2:$D$1708)),0) -> 0.60407548
A11: C0009 | B11: 2 | C11: 13 | D11: 4683.38 | E11: 4 | F11: 4 | G11: 4 | H11: 12 | I11: VIP | J11: Email | K11: 1 | L11: 1477.158 | M11: =_xlfn.RANK.EQ(D11,'Segments clients'!$D$2:$D$1708,0) -> 116 | N11: =SUMIFS('Segments clients'!$D$2:$D$1708,'Segments clients'!$M$2:$M$1708,"<="&M11) -> 708108.61 | O11: =IFERROR(N11/(SUM('Segments clients'!$D$2:$D$1708)),0) -> 0.30294877
A12: C0010 | B12: 1 | C12: 16 | D12: 2896.9272 | E12: 4 | F12: 4 | G12: 4 | H12: 12 | I12: VIP | J12: Google Ads | K12: 1 | L12: 718.7772 | M12: =_xlfn.RANK.EQ(D12,'Segments clients'!$D$2:$D$1708,0) -> 293 | N12: =SUMIFS('Segments clients'!$D$2:$D$1708,'Segments clients'!$M$2:$M$1708,"<="&M12) -> 1361125.3 | O12: =IFERROR(N12/(SUM('Segments clients'!$D$2:$D$1708)),0) -> 0.58232767
A13: C0011 | B13: 26 | C13: 9 | D13: 2204.2026 | E13: 3 | F13: 4 | G13: 4 | H13: 11 | I13: VIP | J13: Google Ads | K13: 1 | L13: 432.2546 | M13: =_xlfn.RANK.EQ(D13,'Segments clients'!$D$2:$D$1708,0) -> 382 | N13: =SUMIFS('Segments clients'!$D$2:$D$1708,'Segments clients'!$M$2:$M$1708,"<="&M13) -> 1587506 | O13: =IFERROR(N13/(SUM('Segments clients'!$D$2:$D$1708)),0) -> 0.67917971
... A1708: C1999 | B1708: 8 | C1708: 2 | D1708: 697.3302 | E1708: 4 | F1708: 3 | G1708: 3 | H1708: 10 | I1708: VIP | J1708: Instagram Ads | K1708: 1 | L1708: 191.5182 | M1708: =_xlfn.RANK.EQ(D1708,'Segments clients'!$D$2:$D$1708,0) -> 799 | N1708: =SUMIFS('Segments clients'!$D$2:$D$1708,'Segments clients'!$M$2:$M$1708,"<="&M1708) -> 2120214.6 | O1708: =IFERROR(N1708/(SUM('Segments clients'!$D$2:$D$1708)),0) -> 0.90708743
